Dflow_project_examples/counter/rtl/counter.v
module counter (
    input clk,
    input rst_n,
    output reg [3:0] count
);

always @(posedge clk or negedge rst_n) begin
    if (!rst_n)
        count <= 4'd0;
    else
        count <= count + 1'b1;
end

endmodule

Dflow_project_examples/Counter_2/tb/counter_tb.sv
`timescale 1ns/1ps

module counter_tb;
    logic clk;
    logic rst_n;
    logic [3:0] count;

    counter dut (
        .clk(clk),
        .rst_n(rst_n),
        .count(count)
    );

    initial begin
        $dumpfile("sim/waves/counter.vcd");
        $dumpvars(0, counter_tb);

        clk = 1'b0;
        rst_n = 1'b0;
        #1;
        rst_n = 1'b1;
        #1;
        repeat (8) begin
            clk = 1'b1;
            #1;
            clk = 1'b0;
            #1;
        end

        if (count !== 4'd8) begin
            $display("FAIL: expected count 8, got %0d", count);
            $fatal(1);
        end

        $display("PASS: counter reached %0d", count);
        $finish;
    end
endmodule

Dflow_project_examples/counter/sim/waves/counter.vcd
$version Generated by VerilatedVcd $end
$timescale 1ps $end
 $scope module counter_tb $end
  $var wire 1 " clk $end
  $var wire 1 # rst_n $end
  $var wire 4 $ count [3:0] $end
  $scope module dut $end
   $var wire 1 " clk $end
   $var wire 1 # rst_n $end
   $var wire 4 $ count [3:0] $end
  $upscope $end
 $upscope $end
$enddefinitions $end


#0
0"
0#
b0000 $
#1000
1#
#2000
1"
b0001 $
#3000
0"
#4000
1"
b0010 $
#5000
0"
#6000
1"
b0011 $
#7000
0"
#8000
1"
b0100 $
#9000
0"
#10000
1"
b0101 $
#11000
0"
#12000
1"
b0110 $
#13000
0"
#14000
1"
b0111 $
#15000
0"
#16000
1"
b1000 $
